anncheck/__init__.py
anncheck-1.3.0.dist-info/LICENSE
anncheck-1.3.0.dist-info/METADATA
anncheck-1.3.0.dist-info/WHEEL
anncheck-1.3.0.dist-info/entry_points.txt
anncheck-1.3.0.dist-info/top_level.txt
anncheck-1.3.0.dist-info/RECORD
