Metadata-Version: 2.1
Name: anncheck
Version: 1.3.0
Summary: A tool to find missing annotations in Python files.
Home-page: https://github.com/Secozzi/anncheck
Author: Folke Ishii
Author-email: folke.ishii@gmail.com
License: MIT license
Platform: UNKNOWN
Classifier: License :: OSI Approved :: MIT License
Classifier: Topic :: Software Development :: Quality Assurance
Classifier: Programming Language :: Python :: 3
Classifier: Programming Language :: Python :: 3.7
Classifier: Programming Language :: Python :: 3.8
Classifier: Programming Language :: Python :: 3.9
Classifier: Programming Language :: Python :: 3 :: Only
Requires-Dist: colorama (>=0.4.4)
Requires-Dist: click (>=7.0.0)
